{
    "page_content": "3GPP TS 38.215 V18.2.0 (2024-03)\nTechnical Specification\n3rd Generation Partnership Project;\nTechnical Specification Group Radio Access Network;\nNR;\nPhysical layer measurements\n(Release 18)\n\t\n\nThe present document has been developed within the 3rd Generation Partnership Project (3GPP TM) and may be further elaborated for the purposes of 3GPP.\nThe present document has not been subject to any approval process by the 3GPP Organizational Partners and shall not be implemented.\nThis Report is provided for future development work within 3GPP only. The Organizational Partners accept no liability for any use of this Specification.\nSpecifications and Reports for implementation of the 3GPP TM system should be obtained via the 3GPP Organizational Partners' Publications Offices.\n\n\n\n\n\nKeywords\n3GPP, New Radio, Layer 1\n\n3GPP\nPostal address\n\n3GPP support office address\n650 Route des Lucioles - Sophia Antipolis\nValbonne - FRANCE\nTel.: +33 4 92 94 42 00 Fax: +33 4 93 65 47 16\nInternet\nhttp://www.3gpp.org\n\nCopyright Notification\nNo part may be reproduced except as authorized by written permission.\nThe copyright and the foregoing restriction extend to reproduction in all media.\n\n\u00a9 2024, 3GPP Organizational Partners (ARIB, ATIS, CCSA, ETSI, TSDSI, TTA, TTC).\nAll rights reserved.\n\nUMTS\u2122 is a Trade Mark of ETSI registered for the benefit of its members\n3GPP\u2122 is a Trade Mark of ETSI registered for the benefit of its Members and of the 3GPP Organizational Partners\nLTE\u2122 is a Trade Mark of ETSI registered for the benefit of its Members and of the 3GPP Organizational Partners\nGSM\u00ae and the GSM logo are registered and owned by the GSM Association\nContents\nForeword\t5\n1\tScope\t6\n2\tReferences\t6\n3\tDefinitions of terms, symbols and abbreviations\t6\n3.1\tTerms\t6\n3.2\tSymbols\t7\n3.3\tAbbreviations\t7\n4\tControl of UE/NG-RAN measurements\t7\n5\tMeasurement capabilities for NR\t8\n5.1\tUE measurement capabilities\t8\n5.1.1\tSS reference signal received power (SS-RSRP)\t9\n5.1.2\tCSI reference signal received power (CSI-RSRP)\t10\n5.1.3\tSS reference signal received quality (SS-RSRQ)\t11\n5.1.4\tCSI reference signal received quality (CSI-RSRQ)\t12\n5.1.5\tSS signal-to-noise and interference ratio (SS-SINR)\t12\n5.1.6\tCSI signal-to-noise and interference ratio (CSI-SINR)\t13\n5.1.7\tVoid\t13\n5.1.8\tVoid\t13\n5.1.9\tUE GNSS Timing of Cell Frames for UE positioning for E-UTRA\t13\n5.1.10\tUE GNSS code measurements\t13\n5.1.11\tUE GNSS carrier phase measurements\t14\n5.1.12\tIEEE 802.11 WLAN RSSI\t14\n5.1.13\tReference signal time difference (RSTD) for E-UTRA\t14\n5.1.14\tSFN and frame timing difference (SFTD)\t14\n5.1.15\tE-UTRA RSRP\t15\n5.1.16\tE-UTRA RSRQ\t15\n5.1.17\tE-UTRA RS-SINR\t16\n5.1.18\tSS reference signal received power per branch (SS-RSRPB)\t16\n5.1.19\tSRS reference signal received power (SRS-RSRP)\t17\n5.1.20\tCLI Received signal strength indicator (CLI-RSSI)\t17\n5.1.21\tReceived Signal Strength Indicator (RSSI)\t17\n5.1.22\tPSBCH reference signal received power (PSBCH-RSRP)\t18\n5.1.23\tPSSCH reference signal received power (PSSCH-RSRP)\t18\n5.1.24\tPS\u0421CH reference signal received power (PSCCH-RSRP)\t19\n5.1.25\tSidelink received signal strength indicator (SL RSSI)\t19\n5.1.26\tSidelink channel occupancy ratio (SL CR)\t19\n5.1.27\tSidelink channel busy ratio (SL CBR)\t20\n5.1.28\tDL PRS reference signal received power (DL PRS-RSRP)\t20\n5.1.29\tDL reference signal time difference (DL RSTD)\t20\n5.1.30\tUE Rx \u2013 Tx time difference\t21\n5.1.31\tSS reference signal antenna relative phase (SS-RSARP)\t21\n5.1.32\tUTRA FDD CPICH RSCP\t22\n5.1.33\tUTRA FDD carrier RSSI\t22\n5.1.34\tUTRA FDD CPICH Ec/No\t22\n5.1.35\tDL PRS reference signal received path power (DL PRS-RSRPP)\t22\n5.1.36\tSidelink PRS reference signal received power (SL PRS-RSRP)\t23\n5.1.37\tSidelink PRS reference signal received path power (SL PRS-RSRPP)\t23\n5.1.38\tSidelink relative time of arrival (TSL-RTOA)\t23\n5.1.39\tSidelink angle of arrival (SL AoA)\t24\n5.1.40\tSidelink Rx \u2013 Tx time difference\t24\n5.1.41\tSidelink reference signal time difference (SL RSTD)\t24\n5.1.42\tDL reference signal carrier phase (DL RSCP)\t25\n5.1.43\tDL reference signal carrier phase difference (DL RSCPD)\t25\n5.1.44\tSidelink PRS received signal strength indicator (SL PRS-RSSI)\t25\n5.1.45\tTime domain channel property (TDCP)\t26\n5.1.46\tUE Rx \u2013 Tx time difference subframe offset\t26\n5.1.47\tDL timing drift\t26\n5.1.48\tSidelink PRS channel occupancy ratio (SL PRS-CR)\t26\n5.1.49\tSidelink PRS channel busy ratio (SL PRS-CBR)\t27\n5.2\tNG-RAN measurement abilities\t27\n5.2.1\tSSS transmit power\t27\n5.2.2\tUL Relative Time of Arrival (TUL-RTOA)\t28\n5.2.3\tgNB Rx \u2013 Tx time difference\t28\n5.2.4\tUL Angle of Arrival (UL AoA)\t29\n5.2.5\tUL SRS reference signal received power (UL SRS-RSRP)\t29\n5.2.6\tUL SRS reference signal received path power (UL SRS-RSRPP)\t29\n5.2.7\tTiming advance (TADV)\t30\n5.2.8\tUL reference signal carrier phase (UL RSCP)\t30\nAnnex A: Change history\t31\n\nForeword\nThis Technical Specification has been produced by the 3rd Generation Partnership Project (3GPP).\nThe contents of the present document are subject to continuing work within the TSG and may change following formal TSG approval. Should the TSG modify the contents of the present document, it will be re-released by the TSG with an identifying change of release date and an increase in version number as follows:\nVersion x.y.z\nwhere:\nx\tthe first digit:\n1\tpresented to TSG for information;\n2\tpresented to TSG for approval;\n3\tor greater indicates TSG approved document under change control.\ny\tthe second digit is incremented for all changes of substance, i.e. technical enhancements, corrections, updates, etc.\nz\tthe third digit is incremented when editorial only changes have been incorporated in the document.\n1\tScope\nThe present document describes the physical layer measurements for NR.\n2\tReferences\nThe following documents contain provisions which, through reference in this text, constitute provisions of the present document.\n[1]\t3GPP TR 21.905: \"Vocabulary for 3GPP Specifications\"\n[2]\t3GPP TS 38.201: \"NR; Physical Layer \u2013 General Description\"\n[3]\t3GPP TS 38.211: \"NR; Physical channels and modulation\"\n[4]\t3GPP TS 38.212: \"NR; Multiplexing and channel coding\"\n[5]\t3GPP TS 38.213: \"NR; Physical layer procedures for control channels\"\n[6]\t3GPP TS 38.214: \"NR; Physical layer procedures for data channels\"\n[7]\t3GPP TS 38.321: \"NR; Medium Access Control (MAC) protocol specification\"\n[8]\t3GPP TS 38.331: \"NR; Radio Resource Control (RRC); Protocol specification\"\n[9]\t3GPP TS 38.104: \"NR; Base Station (BS) radio transmission and reception\"\n[10]\t3GPP TS 36.331: \"Evolved Universal Terrestrial Radio Access (E-UTRA); Radio Resource Control (RRC); Protocol specification\"\n[11]\tIEEE 802.11, Part 11: \"Wireless LAN Medium Access Control (MAC) and Physical Layer (PHY) specifications, IEEE Std.\"\n[12]\t3GPP TS 38.133: \"NR; Requirements for support of radio resource management\"\n[13]\t3GPP TS 36.211: \"Evolved Universal Terrestrial Radio Access (E-UTRA); Physical channels and modulation\"\n[14]\t3GPP TS 38.509: \"5GS; Special conformance testing functions for User Equipment (UE)\"\n[15]\t3GPP TS 38.901: \"Study on channel model for frequencies from 0.5 to 100 GHz\"\n[16]\t3GPP TS 38.455: \"NR Positioning Protocol A (NRPPa)\"\n[17]\t3GPP TS 37.213: \"Physical layer procedures for shared spectrum channel access\"\n[18]\t3GPP TS 38.305: \"NG Radio Access Network (NG-RAN); Stage 2 functional specification of User Equipment (UE) positioning in NG-RAN\"\n3\tDefinitions of terms, symbols and abbreviations\n3.1\tTerms\nFor the purposes of the present document, the terms and definitions given in TR\u00a021.905\u00a0[1] and the following apply. A term defined in the present document takes precedence over the definition of the same term, if any, in TR\u00a021.905\u00a0[1].\n3.2\tSymbols\nFor the purposes of the present document, the following symbols apply:\n3.3\tAbbreviations\nFor the purposes of the present document, the abbreviations given in TR\u00a021.905 [1] and the following apply. An abbreviation defined in the present document takes precedence over the definition of the same abbreviation, if any, in TR\u00a021.905\u00a0[1].\nARFCN\tAbsolute Radio-Frequency Channel Number\nCLI\tCross Link Interference \nCSI-RSRP\tCSI Reference Signal Received Power\nCSI-RSRQ\tCSI Reference Signal Received Quality\nE-UTRAN\tEvolved UTRAN\nGNSS\tGlobal Navigation Satellite System\nGSM\tGlobal System for Mobile communication\nLBT\tListen Before Talk \nSRS\tSounding Reference Signal \nSS-RSRP\tSynchronization Signal Reference Signal Received Power\nSS-RSRQ\tSynchronization Signal Reference Signal Received Quality\nUTRAN\tUniversal Terrestrial Radio Access Network\n\n4\tControl of UE/NG-RAN measurements\nIn this clause the general measurement control concept of the higher layers is briefly described to provide an understanding on how L1 measurements are initiated and controlled by higher layers.\nWith the measurement specifications L1 provides measurement capabilities for the UE and NG-RAN. These measurements can be classified in different reported measurement types: intra-frequency, inter-frequency, inter-system, traffic volume, quality and UE internal measurements.\nIn the L1 measurement definitions, see clause 5, the measurements are categorised as measurements in the UE or measurements in the NG-RAN.\n\n5\tMeasurement capabilities for NR\n5.1\tUE measurement capabilities\nThe structure of the table defining a UE measurement quantity is shown below.\n\n\n5.1.1\tSS reference signal received power (SS-RSRP)\n\nNOTE 1:\tThe number of resource elements within the measurement period that are used by the UE to determine SS-RSRP is left up to the UE implementation with the limitation that corresponding measurement accuracy requirements have to be fulfilled.\nNOTE 2:\tThe power per resource element is determined from the energy received during the useful part of the symbol, excluding the CP.\n\n5.1.2\tCSI reference signal received power (CSI-RSRP)\n\nNOTE 1:\tThe number of resource elements within the considered measurement frequency bandwidth and within the measurement period that are used by the UE to determine CSI-RSRP is left up to the UE implementation with the limitation that corresponding measurement accuracy requirements have to be fulfilled.\nNOTE 2:\tThe power per resource element is determined from the energy received during the useful part of the symbol, excluding the CP.\n\n5.1.3\tSS reference signal received quality (SS-RSRQ)\n\n\nTable 5.1.3-1: NR Carrier RSSI measurement symbols\n\n5.1.4\tCSI reference signal received quality (CSI-RSRQ)\n\n\n5.1.5\tSS signal-to-noise and interference ratio (SS-SINR)\n\n\n5.1.6\tCSI signal-to-noise and interference ratio (CSI-SINR)\n\n\n5.1.7\tVoid\n\n5.1.8\tVoid\n\n5.1.9\tUE GNSS Timing of Cell Frames for UE positioning for E-UTRA\n\n\n5.1.10\tUE GNSS code measurements\n\n\n5.1.11\tUE GNSS carrier phase measurements\n\n\n5.1.12\tIEEE 802.11 WLAN RSSI\n\n\n5.1.13\tReference signal time difference (RSTD) for E-UTRA\n\n\n5.1.14\tSFN and frame timing difference (SFTD)\n\n\n5.1.15\tE-UTRA RSRP\n\nNOTE 1:\tThe number of resource elements within the considered measurement frequency bandwidth and within the measurement period that are used by the UE to determine E-UTRA RSRP is left up to the UE implementation with the limitation that corresponding measurement accuracy requirements have to be fulfilled.\nNOTE 2:\tThe power per resource element is determined from the energy received during the useful part of the symbol, excluding the CP.\n\n5.1.16\tE-UTRA RSRQ\n\n\n5.1.17\tE-UTRA RS-SINR\n\n\n5.1.18\tSS reference signal received power per branch (SS-RSRPB)\n\n\nNOTE 1:\tThe number of resource elements within the measurement period that are used by the UE to determine SS-RSRPB is left up to the UE implementation with the limitation that corresponding measurement accuracy requirements have to be fulfilled.\nNOTE 2:\tThe power per resource element is determined from the energy received during the useful part of the symbol, excluding the CP. \nNOTE 3:\tThis UE measurement is defined only for conformance test purposes. It is described along with test control entity signalling in [14].\n5.1.19\tSRS reference signal received power (SRS-RSRP)\n\n\n5.1.20\tCLI Received signal strength indicator (CLI-RSSI)\n\n\n5.1.21\tReceived Signal Strength Indicator (RSSI)\n\n\n5.1.22\tPSBCH reference signal received power (PSBCH-RSRP)\n\n\nNOTE 1:\tThe number of resource elements within the considered measurement frequency bandwidth and within the measurement period that are used by the UE to determine PSBCH-RSRP is left up to the UE implementation with the limitation that corresponding measurement accuracy requirements have to be fulfilled.\nNOTE 2:\tThe power per resource element is determined from the energy received during the useful part of the symbol, excluding the CP. \nNOTE 3:\tIt is up to UE implementation to use PSBCH DMRS only or both S-SSS and PSBCH DMRS for PSBCH-RSRP.\n5.1.23\tPSSCH reference signal received power (PSSCH-RSRP)\n\n\nNOTE 1:\tThe power per resource element is determined from the energy received during the useful part of the symbol, excluding the CP.\n5.1.24\tPS\u0421CH reference signal received power (PSCCH-RSRP)\n\n\nNOTE 1:\tThe power per resource element is determined from the energy received during the useful part of the symbol, excluding the CP.\n5.1.25\tSidelink received signal strength indicator (SL RSSI)\n\n\n5.1.26\tSidelink channel occupancy ratio (SL CR)\n\n\nNOTE 1:\ta is a positive integer and b is 0 or a positive integer; a and b are determined by UE implementation with a+b+1 = 1000 or 1000\u00b72\u00b5 slots, according to higher layer parameter sl-TimeWindowSizeCR, b < (a+b+1)/2, and n+b shall not exceed the last transmission opportunity of the grant for the current transmission.\nNOTE 2:\tSL CR is evaluated for each (re)transmission.\nNOTE 3:\tIn evaluating SL CR, the UE shall assume the transmission parameter used at slot n is reused according to the existing grant(s) in slot [n+1, n+b] without packet dropping.\nNOTE 4:\tThe slot index is based on physical slot index.\nNOTE 5:\tSL CR can be computed per priority level\nNOTE 6:\tA resource is considered granted if it is a member of a selected sidelink grant as defined in TS\u00a038.321\u00a0[7].\n5.1.27\tSidelink channel busy ratio (SL CBR)\n\n\nNOTE 1:\tThe slot index is based on physical slot index.\n5.1.28\tDL PRS reference signal received power (DL PRS-RSRP)\n\n\n5.1.29\tDL reference signal time difference (DL RSTD)\n\n\n5.1.30\tUE Rx \u2013 Tx time difference\n\n\n5.1.31\tSS reference signal antenna relative phase (SS-RSARP)\n\n\nNOTE 1:\tThe number of resource elements within the measurement period that are used by the UE to determine SS-RSARP is left up to the UE implementation with the limitation that corresponding measurement accuracy requirements have to be fulfilled.\nNOTE 2:\tThe phase per resource element is determined from the energy received during the useful part of the symbol, excluding the CP.\nNOTE 3:\tThis UE measurement is defined only for conformance test purposes. It is described along with test control entity signalling in [14].\n5.1.32\tUTRA FDD CPICH RSCP\n\n\n5.1.33\tUTRA FDD carrier RSSI\n\nNOTE:\tThis definition does not correspond to a reported measurement. This definition is just an intermediate definition used in the definition of UTRA FDD CPICH Ec/No.\n5.1.34\tUTRA FDD CPICH Ec/No\n\n\n5.1.35\tDL PRS reference signal received path power (DL PRS-RSRPP)\n\n\n5.1.36\tSidelink PRS reference signal received power (SL PRS-RSRP)\n\n\n5.1.37\tSidelink PRS reference signal received path power (SL PRS-RSRPP)\n\n\n5.1.38\tSidelink relative time of arrival (TSL-RTOA)\n\n\n5.1.39\tSidelink angle of arrival (SL AoA)\n\n\n5.1.40\tSidelink Rx \u2013 Tx time difference\n\n\n5.1.41\tSidelink reference signal time difference (SL RSTD)\n\n\n5.1.42\tDL reference signal carrier phase (DL RSCP)\n\n\n5.1.43\tDL reference signal carrier phase difference (DL RSCPD)\n\n\n5.1.44\tSidelink PRS received signal strength indicator (SL PRS-RSSI)\n\n\n5.1.45\tTime domain channel property (TDCP)\n\n\n5.1.46\tUE Rx \u2013 Tx time difference subframe offset\n\n\n5.1.47\tDL timing drift\n\n\n5.1.48\tSidelink PRS channel occupancy ratio (SL PRS-CR)\n\n\nNOTE 1:\ta is a positive integer and b is 0 or a positive integer; a and b are determined by UE implementation with a+b+1 = 1000 or 1000\u00b72\u00b5 slots, according to higher layer parameter sl-TimeWindowSizeCR-Dedicated-SL-PRS-RP, b < (a+b+1)/2, and n+b shall not exceed the last transmission opportunity of the grant for the current transmission.\nNOTE 2:\tSL PRS-CR is evaluated for each (re)transmission.\nNOTE 3:\tIn evaluating SL PRS-CR, the UE shall assume the transmission parameter used at slot n is reused according to the existing grant(s) in slot [n+1, n+b] without dropping.\nNOTE 4:\tThe slot index is based on physical slot index.\nNOTE 5:\tSL PRS-CR can be computed per priority level\nNOTE 6:\tA resource is considered granted if it is a member of a selected sidelink grant as defined in TS\u00a038.321\u00a0[7].\n5.1.49\tSidelink PRS channel busy ratio (SL PRS-CBR)\n\n\nNOTE 1:\tThe slot index is based on physical slot index.\n5.2\tNG-RAN measurement abilities\nThe structure of the table defining a NG-RAN measurement quantity is shown below.\n\n\n5.2.1\tSSS transmit power\n\n\n5.2.2\tUL Relative Time of Arrival (TUL-RTOA)\n\n\n5.2.3\tgNB Rx \u2013 Tx time difference\n\n\n5.2.4\tUL Angle of Arrival (UL AoA)\n\n\n5.2.5\tUL SRS reference signal received power (UL SRS-RSRP)\n\n\n5.2.6\tUL SRS reference signal received path power (UL SRS-RSRPP)\n\n\n5.2.7\tTiming advance (TADV)\n\n\n5.2.8\tUL reference signal carrier phase (UL RSCP)\n\n\nAnnex A:\nChange history\n\n",
    "metadata": {
        "title0": "3GPP TS 38.215",
        "title1": "Technical Specification Group Radio Access Network",
        "title2": "NR",
        "title3": "Physical layer measurements",
        "Release": 18,
        "Version": "V18.2.0",
        "Publish_time": "2024-03"
    }
}